Workbook

Sheet Components
A2: QR and identifiable research funding components
A3: Academic year | B3: Broad discipline | C3: Mainstream QR | D3: London QR | E3: RDP QR | F3: Charity QR | G3: Business QR | H3: Total QR | I3: Research Councils | J3: Charities | K3: Central government | L3: Industry | M3: Overseas | N3: Identifiable funding
A4: 2010-11 | B4: Arts and Humanities | C4: 172953776 | D4: 4991023 | E4: 30137431 | F4: 6085230 | G4: 1609880.4 | H4: =SUM(C4:G4) -> 2.1577734e+08 | I4: 49585000 | J4: 20057000 | K4: 7067000 | L4: 5196000 | M4: 18720000 | N4: =SUM(H4:M4) -> 3.1640234e+08
A5: 2010-11 | B5: Social Sciences | C5: 200714277 | D5: 5884279 | E5: 40488742 | F5: 9552288 | G5: 6468424.6 | H5: =SUM(C5:G5) -> 2.6310801e+08 | I5: 103473000 | J5: 28833000 | K5: 80087000 | L5: 22782000 | M5: 64329000 | N5: =SUM(H5:M5) -> 5.6261201e+08
A6: 2010-11 | B6: STEM | C6: 486959641 | D6: 10686038 | E6: 92858256 | F6: 38812237 | G6: 39712709 | H6: =SUM(C6:G6) -> 6.6902888e+08 | I6: 803255000 | J6: 191784000 | K6: 164676000 | L6: 143992000 | M6: 316421000 | N6: =SUM(H6:M6) -> 2.2891569e+09
A7: 2010-11 | B7: Health | C7: 236140341 | D7: 11828912 | E7: 41711987 | F7: 143072213 | G7: 15878026 | H7: =SUM(C7:G7) -> 4.4863148e+08 | I7: 283570000 | J7: 519771000 | K7: 374729000 | L7: 56695000 | M7: 261331000 | N7: =SUM(H7:M7) -> 1.9447275e+09
A8: 2011-12 | B8: Arts and Humanities | C8: 166110726 | D8: 4836022 | E8: 30341178 | F8: 6148161 | G8: 1163720.1 | H8: =SUM(C8:G8) -> 2.0859981e+08 | I8: 46684000 | J8: 21036000 | K8: 5857000 | L8: 4714000 | M8: 25947000 | N8: =SUM(H8:M8) -> 3.1283781e+08
A9: 2011-12 | B9: Social Sciences | C9: 192660106 | D9: 5733347 | E9: 40622333 | F9: 9340163 | G9: 4646640.4 | H9: =SUM(C9:G9) -> 2.5300259e+08 | I9: 97292000 | J9: 26942000 | K9: 67338000 | L9: 21931000 | M9: 68049000 | N9: =SUM(H9:M9) -> 5.3455459e+08
A10: 2011-12 | B10: STEM | C10: 466947826 | D10: 10280145 | E10: 92313665 | F10: 39072118 | G10: 37800388 | H10: =SUM(C10:G10) -> 6.4641414e+08 | I10: 780004000 | J10: 204128000 | K10: 146708000 | L10: 146777000 | M10: 378054000 | N10: =SUM(H10:M10) -> 2.3020851e+09
A11: 2011-12 | B11: Health | C11: 227056158 | D11: 11533967 | E11: 41919250 | F11: 142961516 | G11: 20058291 | H11: =SUM(C11:G11) -> 4.4352918e+08 | I11: 272355000 | J11: 526011000 | K11: 412512000 | L11: 56478000 | M11: 290450000 | N11: =SUM(H11:M11) -> 2.0013352e+09
A12: 2012-13 | B12: Arts and Humanities | C12: 158386043 | D12: 4652637 | E12: 35087629 | F12: 5411357.7 | G12: 852511.92 | H12: =SUM(C12:G12) -> 2.0439018e+08 | I12: 50827000 | J12: 21211000 | K12: 4597000 | L12: 4681000 | M12: 32513000 | N12: =SUM(H12:M12) -> 3.1821918e+08
A13: 2012-13 | B13: Social Sciences | C13: 178639170 | D13: 5369082 | E13: 44460471 | F13: 6692490.2 | G13: 4369603.6 | H13: =SUM(C13:G13) -> 2.3953082e+08 | I13: 93344000 | J13: 27327000 | K13: 61308000 | L13: 21287000 | M13: 81318000 | N13: =SUM(H13:M13) -> 5.2411482e+08
A14: 2012-13 | B14: STEM | C14: 456166539 | D14: 10061481 | E14: 111829094 | F14: 50358082 | G14: 38173238 | H14: =SUM(C14:G14) -> 6.6658843e+08 | I14: 798706000 | J14: 211375000 | K14: 152998000 | L14: 153221000 | M14: 451267000 | N14: =SUM(H14:M14) -> 2.4341554e+09
A15: 2012-13 | B15: Health | C15: 225303226 | D15: 11580109 | E15: 48819214 | F15: 1.3506003e+08 | G15: 20273680 | H15: =SUM(C15:G15) -> 4.4103626e+08 | I15: 279323000 | J15: 553423000 | K15: 445440000 | L15: 56623000 | M15: 324994000 | N15: =SUM(H15:M15) -> 2.1008393e+09
... A63: 2024-25 | B63: Health | C63: 321387565 | D63: 13085828 | E63: 96278257 | F63: 1.4670741e+08 | G63: 52553564 | H63: =SUM(C63:G63) -> 6.3001263e+08 | I63: 469450000 | J63: 705160000 | K63: 712698000 | L63: 125944000 | M63: 488639000 | N63: =SUM(H63:M63) -> 3.1319036e+09

Sheet Annual series
A2: QR share of identifiable research funding by broad discipline
A3: All values are England totals. Percentages are nominal funding shares; the shaded years use reconstructed QR subject allocations.
A4: Academic year | B4: Broad discipline | C4: QR data status | D4: Total QR (£) | E4: Identifiable funding (£) | F4: QR share | G4: Mainstream QR share | H4: Other QR share | I4: Sensitivity low | J4: Sensitivity high
A5: 2010-11 | B5: Arts and Humanities | C5: Published QR; provider support funds allocated by HESA income | D5: =Components!H4 -> 2.1577734e+08 | E5: =Components!N4 -> 3.1640234e+08 | F5: =D5/E5 -> 0.68197138 | G5: =Components!C4/E5 -> 0.5466261 | H5: =SUM(Components!D4:G4)/E5 -> 0.13534528 | I5: 0.68197138 | J5: 0.68197138
A6: 2010-11 | B6: Social Sciences | C6: Published QR; provider support funds allocated by HESA income | D6: =Components!H5 -> 2.6310801e+08 | E6: =Components!N5 -> 5.6261201e+08 | F6: =D6/E6 -> 0.46765445 | G6: =Components!C5/E6 -> 0.35675434 | H6: =SUM(Components!D5:G5)/E6 -> 0.11090011 | I6: 0.46765445 | J6: 0.46765445
A7: 2010-11 | B7: STEM | C7: Published QR; provider support funds allocated by HESA income | D7: =Components!H6 -> 6.6902888e+08 | E7: =Components!N6 -> 2.2891569e+09 | F7: =D7/E7 -> 0.29225995 | G7: =Components!C6/E7 -> 0.21272445 | H7: =SUM(Components!D6:G6)/E7 -> 0.079535501 | I7: 0.29225995 | J7: 0.29225995
A8: 2010-11 | B8: Health | C8: Published QR; provider support funds allocated by HESA income | D8: =Components!H7 -> 4.4863148e+08 | E8: =Components!N7 -> 1.9447275e+09 | F8: =D8/E8 -> 0.23069118 | G8: =Components!C7/E8 -> 0.12142593 | H8: =SUM(Components!D7:G7)/E8 -> 0.10926525 | I8: 0.23069118 | J8: 0.23069118
A9: 2011-12 | B9: Arts and Humanities | C9: Published QR; provider support funds allocated by HESA income | D9: =Components!H8 -> 2.0859981e+08 | E9: =Components!N8 -> 3.1283781e+08 | F9: =D9/E9 -> 0.66679858 | G9: =Components!C8/E9 -> 0.53098034 | H9: =SUM(Components!D8:G8)/E9 -> 0.13581824 | I9: 0.66679858 | J9: 0.66679858
A10: 2011-12 | B10: Social Sciences | C10: Published QR; provider support funds allocated by HESA income | D10: =Components!H9 -> 2.5300259e+08 | E10: =Components!N9 -> 5.3455459e+08 | F10: =D10/E10 -> 0.47329608 | G10: =Components!C9/E10 -> 0.36041241 | H10: =SUM(Components!D9:G9)/E10 -> 0.11288367 | I10: 0.47329608 | J10: 0.47329608
A11: 2011-12 | B11: STEM | C11: Published QR; provider support funds allocated by HESA income | D11: =Components!H10 -> 6.4641414e+08 | E11: =Components!N10 -> 2.3020851e+09 | F11: =D11/E11 -> 0.28079506 | G11: =Components!C10/E11 -> 0.20283691 | H11: =SUM(Components!D10:G10)/E11 -> 0.077958158 | I11: 0.28079506 | J11: 0.28079506
A12: 2011-12 | B12: Health | C12: Published QR; provider support funds allocated by HESA income | D12: =Components!H11 -> 4.4352918e+08 | E12: =Components!N11 -> 2.0013352e+09 | F12: =D12/E12 -> 0.22161664 | G12: =Components!C11/E12 -> 0.11345234 | H12: =SUM(Components!D11:G11)/E12 -> 0.1081643 | I12: 0.22161664 | J12: 0.22161664
A13: 2012-13 | B13: Arts and Humanities | C13: Published QR; provider support funds allocated by HESA income | D13: =Components!H12 -> 2.0439018e+08 | E13: =Components!N12 -> 3.1821918e+08 | F13: =D13/E13 -> 0.64229372 | G13: =Components!C12/E13 -> 0.49772626 | H13: =SUM(Components!D12:G12)/E13 -> 0.14456745 | I13: 0.64229372 | J13: 0.64229372
A14: 2012-13 | B14: Social Sciences | C14: Published QR; provider support funds allocated by HESA income | D14: =Components!H13 -> 2.3953082e+08 | E14: =Components!N13 -> 5.2411482e+08 | F14: =D14/E14 -> 0.45701974 | G14: =Components!C13/E14 -> 0.34083976 | H14: =SUM(Components!D13:G13)/E14 -> 0.11617998 | I14: 0.45701974 | J14: 0.45701974
A15: 2012-13 | B15: STEM | C15: Published QR; provider support funds allocated by HESA income | D15: =Components!H14 -> 6.6658843e+08 | E15: =Components!N14 -> 2.4341554e+09 | F15: =D15/E15 -> 0.27384793 | G15: =Components!C14/E15 -> 0.18740239 | H15: =SUM(Components!D14:G14)/E15 -> 0.086445546 | I15: 0.27384793 | J15: 0.27384793
A16: 2012-13 | B16: Health | C16: Published QR; provider support funds allocated by HESA income | D16: =Components!H15 -> 4.4103626e+08 | E16: =Components!N15 -> 2.1008393e+09 | F16: =D16/E16 -> 0.20993337 | G16: =Components!C15/E16 -> 0.10724439 | H16: =SUM(Components!D15:G15)/E16 -> 0.10268898 | I16: 0.20993337 | J16: 0.20993337
... A64: 2024-25 | B64: Health | C64: Published QR; RDP subject mix carried forward from 2023-24 | D64: =Components!H63 -> 6.3001263e+08 | E64: =Components!N63 -> 3.1319036e+09 | F64: =D64/E64 -> 0.20115965 | G64: =Components!C63/E64 -> 0.10261732 | H64: =SUM(Components!D63:G63)/E64 -> 0.098542324 | I64: 0.20115965 | J64: 0.20115965

Sheet Summary
A2: The role of QR funding across disciplines
A3: Reconstruction of HEFCE's 2010/11 result and extension to the latest common QR/HESA year (2024/25)
A5: 2010/11 Arts and Humanities reproduction | E5: 2024/25 QR share
A6: Mainstream QR | B6: Other QR | C6: Total QR share | E6: A&H | F6: Social Sciences | G6: STEM | H6: Health
A7: ='Annual series'!G5 -> 0.5466261 | B7: ='Annual series'!H5 -> 0.13534528 | C7: ='Annual series'!F5 -> 0.68197138 | E7: ='Annual series'!F61 -> 0.57297571 | F7: ='Annual series'!F62 -> 0.3607499 | G7: ='Annual series'!F63 -> 0.2175528 | H7: ='Annual series'!F64 -> 0.20115965
A9: The report's ‘around 70%’ is 68.20% on the reconstructed data. QR remains the largest identifiable stream for A&H in 2024/25.
A12: Academic year | B12: Arts and Humanities | C12: Social Sciences | D12: STEM | E12: Health
A13: 2010-11 | B13: ='Annual series'!F5 -> 0.68197138 | C13: ='Annual series'!F6 -> 0.46765445 | D13: ='Annual series'!F7 -> 0.29225995 | E13: ='Annual series'!F8 -> 0.23069118
A14: 2011-12 | B14: ='Annual series'!F9 -> 0.66679858 | C14: ='Annual series'!F10 -> 0.47329608 | D14: ='Annual series'!F11 -> 0.28079506 | E14: ='Annual series'!F12 -> 0.22161664
A15: 2012-13 | B15: ='Annual series'!F13 -> 0.64229372 | C15: ='Annual series'!F14 -> 0.45701974 | D15: ='Annual series'!F15 -> 0.27384793 | E15: ='Annual series'!F16 -> 0.20993337
A16: 2013-14 | B16: ='Annual series'!F17 -> 0.62039759 | C16: ='Annual series'!F18 -> 0.44330224 | D16: ='Annual series'!F19 -> 0.25703085 | E16: ='Annual series'!F20 -> 0.20433283
A17: 2014-15 | B17: ='Annual series'!F21 -> 0.60573035 | C17: ='Annual series'!F22 -> 0.4329968 | D17: ='Annual series'!F23 -> 0.23911231 | E17: ='Annual series'!F24 -> 0.18894826
A18: 2015-16 | B18: ='Annual series'!F25 -> 0.58193226 | C18: ='Annual series'!F26 -> 0.42625391 | D18: ='Annual series'!F27 -> 0.22672967 | E18: ='Annual series'!F28 -> 0.18787748
A19: 2016-17 | B19: ='Annual series'!F29 -> 0.56228825 | C19: ='Annual series'!F30 -> 0.4099907 | D19: ='Annual series'!F31 -> 0.22200551 | E19: ='Annual series'!F32 -> 0.18954145
A20: 2017-18 | B20: ='Annual series'!F33 -> 0.54355226 | C20: ='Annual series'!F34 -> 0.39722679 | D20: ='Annual series'!F35 -> 0.21046651 | E20: ='Annual series'!F36 -> 0.1840123
A21: 2018-19 | B21: ='Annual series'!F37 -> 0.53440238 | C21: ='Annual series'!F38 -> 0.39405995 | D21: ='Annual series'!F39 -> 0.20302239 | E21: ='Annual series'!F40 -> 0.18027329
A22: 2019-20 | B22: ='Annual series'!F41 -> 0.54390862 | C22: ='Annual series'!F42 -> 0.40423283 | D22: ='Annual series'!F43 -> 0.21721999 | E22: ='Annual series'!F44 -> 0.18932586
A23: 2020-21 | B23: ='Annual series'!F45 -> 0.54033785 | C23: ='Annual series'!F46 -> 0.38024564 | D23: ='Annual series'!F47 -> 0.2153169 | E23: ='Annual series'!F48 -> 0.18501297
A24: 2021-22 | B24: ='Annual series'!F49 -> 0.51739465 | C24: ='Annual series'!F50 -> 0.3559055 | D24: ='Annual series'!F51 -> 0.20938348 | E24: ='Annual series'!F52 -> 0.16994445
A25: 2022-23 | B25: ='Annual series'!F53 -> 0.55398431 | C25: ='Annual series'!F54 -> 0.36924291 | D25: ='Annual series'!F55 -> 0.23565823 | E25: ='Annual series'!F56 -> 0.19275924
A26: 2023-24 | B26: ='Annual series'!F57 -> 0.5686103 | C26: ='Annual series'!F58 -> 0.36282009 | D26: ='Annual series'!F59 -> 0.22167466 | E26: ='Annual series'!F60 -> 0.19453656
A27: 2024-25 | B27: ='Annual series'!F61 -> 0.57297571 | C27: ='Annual series'!F62 -> 0.3607499 | D27: ='Annual series'!F63 -> 0.2175528 | E27: ='Annual series'!F64 -> 0.20115965
A30: Reading the bridge | B30: 2015/16–2018/19 use the published national pots and reconstruct the missing subject distribution. Sensitivity columns show the effect of using the 2014/15 rather than 2019/20 RDP discipline mix.

Sheet Method
A2: Method, definitions and source register
A4: Topic | B4: Method used | C4: Implication | D4: Primary source
A5: Scope | B5: England; academic years 2010/11–2024/25; four broad disciplines. | C5: 2024/25 is the latest year with both QR allocations and a HESA denominator. | D5: HEFCE/Research England; HESA Finance Table 5/5b
A6: QR numerator | B6: Mainstream QR + London weighting + RDP supervision + charity support + business research element. | C6: National Research Libraries and temporary GCRF QR are excluded for consistency with the 2014 figure. | D6: HEFCE/Research England detailed allocation tables
A7: Denominator | B7: QR numerator + Research Councils + UK charities + central government + UK industry + overseas research income. | C7: HESA UK other sources and the source-table total are excluded, matching Figure 9.3. | D7: HESA Finance Plus Table 5b / Table 5 CSV
A8: 2010/11 result | B8: Provider support-fund grants are split by the provider's qualifying HESA income across cost centres, then aggregated. | C8: A&H: 54.66% mainstream QR + 13.53% other QR = 68.20% total QR. | D8: resdata1011.xls; business1011.xls; HE_Finance_Plus_2010-11.zip
A9: 2015/16–2018/19 mainstream | B9: Use the 2019/20 REF2014 UOA distribution, reverse UOA 4's 1.60 cost weight to 1.42, and scale to the published annual mainstream-plus-London pot. | C9: Reconstructs the stable formula base while excluding separately identified GCRF additions. | D9: HEFCE funding guides; RE 2019/20 data-source note
A10: 2015/16–2018/19 RDP | B10: Use the adjusted 2019/20 UOA distribution and scale to each annual RDP pot. | C10: Exact values require unpublished student-level derived inputs; low/high columns use 2014/15 and 2019/20 discipline mixes as endpoint sensitivity. | D10: RE RDP 2019/20 workbook; HEFCE/RE funding guides
A11: Charity/business QR | B11: Split published provider grants by qualifying charity/industry income across that provider's HESA cost centres. Unmatched residuals use the national qualifying-income mix. | C11: The grant totals are observed; their discipline allocation is constructed consistently for every year. | D11: HEFCE/RE provider grants; HESA Finance Table 5
A12: 2024/25 RDP | B12: Carry forward each provider's 2023/24 UOA shares and scale to its published 2024/25 RDP total. | C12: Matches Research England's stated carry-forward approach; new providers use national shares. | D12: Research England provider grant tables 2023/24 and 2024/25
A13: Broad disciplines | B13: Legacy HESA: Health 01,02,04–08; STEM 03,10–25 selected; Social 26–29,34,38,41; A&H 30,31,33,35,37. New HESA: Health 101–107; STEM 109–123; Social 108,124,127–136; A&H 125–126,137–145. | C13: Keeps the report's disciplinary logic across the 2012/13 cost-centre change. | D13: HESA cost-centre classifications
A14: REF UOA mapping | B14: REF2014: Health 1–4; STEM 5–16; Social 17–26; A&H 27–36. REF2021: Health 1–4; STEM 5–13; Social 14 and 16–24; A&H 15 and 25–34. | C14: Architecture stays in STEM; archaeology/area studies stay in A&H. | D14: REF UOA definitions and HESA mapping workbook
A15: Prices | B15: Nominal pounds; shares are calculated within each year. | C15: No deflator is required for the percentage series. | D15: All source tables
A16: Interpretation | B16: The metric measures QR as a share of identifiable income streams, not total research resources or full economic cost. | C16: Changes may reflect both QR allocations and movements in external income. | D16: HEFCE 2014 report, Figure 9.3
A19: Source links
A20: Source | B20: Location | C20: Use
A21: 2014 report | B21: /Users/benjohnson/dev/science/qrahss/2014_qrreview.pdf | C21: Attached source report
A22: RE 2019/20 detailed QR data | B22: https://www.ukri.org/publications/funding-allocations-2019-2020-quality-related-research-funding-data/ | C22: Mainstream, London and RDP UOA workbooks
A23: RE 2023/24 provider tables | B23: https://www.ukri.org/publications/higher-education-provider-grant-data-tables-2023-to-2024/ | C23: Provider and UOA allocations
A24: RE 2024/25 provider tables | B24: https://www.ukri.org/publications/higher-education-provider-grant-data-tables-2024-to-2025/ | C24: Latest common-year QR allocations
A25: Local source inventory | B25: /Users/benjohnson/dev/science/qrahss/data_sources/UKRI_QR_download_manifest.md | C25: Downloaded workbooks and provenance

Sheet Checks
A2: QR control-total checks
A3: Calculated broad-discipline totals reconcile to the published QR component totals; tolerance is £2 for source rounding.
A5: Academic year | B5: Published/control QR (£) | C5: Calculated QR (£) | D5: Difference (£) | E5: Status
A6: 2010-11 | B6: 1596545711 | C6: =SUM(Components!H4:H7) -> 1596545711 | D6: =C6-B6 -> 0 | E6: =IF(ABS(D6)<=2,"OK","Review") -> OK
A7: 2011-12 | B7: 1551545721 | C7: =SUM(Components!H8:H11) -> 1551545721 | D7: =C7-B7 -> 0 | E7: =IF(ABS(D7)<=2,"OK","Review") -> OK
A8: 2012-13 | B8: 1551545692 | C8: =SUM(Components!H12:H15) -> 1551545692 | D8: =C8-B8 -> 0 | E8: =IF(ABS(D8)<=2,"OK","Review") -> OK
A9: 2013-14 | B9: 1551545692 | C9: =SUM(Components!H16:H19) -> 1551545692 | D9: =C9-B9 -> 0 | E9: =IF(ABS(D9)<=2,"OK","Review") -> OK
A10: 2014-15 | B10: 1551498547 | C10: =SUM(Components!H20:H23) -> 1551498547 | D10: =C10-B10 -> 0 | E10: =IF(ABS(D10)<=2,"OK","Review") -> OK
A11: 2015-16 | B11: 1552000000 | C11: =SUM(Components!H24:H27) -> 1552000000 | D11: =C11-B11 -> 0 | E11: =IF(ABS(D11)<=2,"OK","Review") -> OK
A12: 2016-17 | B12: 1552000000 | C12: =SUM(Components!H28:H31) -> 1.552e+09 | D12: =C12-B12 -> 0 | E12: =IF(ABS(D12)<=2,"OK","Review") -> OK
A13: 2017-18 | B13: 1552000000 | C13: =SUM(Components!H32:H35) -> 1552000000 | D13: =C13-B13 -> 0 | E13: =IF(ABS(D13)<=2,"OK","Review") -> OK
A14: 2018-19 | B14: 1578000000 | C14: =SUM(Components!H36:H39) -> 1578000000 | D14: =C14-B14 -> 0 | E14: =IF(ABS(D14)<=2,"OK","Review") -> OK
A15: 2019-20 | B15: 1622387305 | C15: =SUM(Components!H40:H43) -> 1622387305 | D15: =C15-B15 -> 0 | E15: =IF(ABS(D15)<=2,"OK","Review") -> OK
A16: 2020-21 | B16: 1622387117 | C16: =SUM(Components!H44:H47) -> 1.6223871e+09 | D16: =C16-B16 -> 0 | E16: =IF(ABS(D16)<=2,"OK","Review") -> OK
A17: 2021-22 | B17: 1622387148 | C17: =SUM(Components!H48:H51) -> 1622387148 | D17: =C17-B17 -> 0 | E17: =IF(ABS(D17)<=2,"OK","Review") -> OK
A18: 2022-23 | B18: 1967226170 | C18: =SUM(Components!H52:H55) -> 1967226170 | D18: =C18-B18 -> 0 | E18: =IF(ABS(D18)<=2,"OK","Review") -> OK
A19: 2023-24 | B19: 1974225843 | C19: =SUM(Components!H56:H59) -> 1974225843 | D19: =C19-B19 -> 0 | E19: =IF(ABS(D19)<=2,"OK","Review") -> OK
A20: 2024-25 | B20: 1979999992 | C20: =SUM(Components!H60:H63) -> 1.98e+09 | D20: =C20-B20 -> 0 | E20: =IF(ABS(D20)<=2,"OK","Review") -> OK
A23: Additional check | B23: Result | C23: Meaning
A24: 2010/11 A&H QR share | B24: ='Annual series'!F5 -> 0.68197138 | C24: Should round to the report's ‘around 70%’
A25: 2010/11 component identity | B25: ='Annual series'!G5+'Annual series'!H5-'Annual series'!F5 -> 0 | C25: Mainstream share + other QR share = total QR share
A26: Reconstructed years | B26: 4 | C26: 2015/16–2018/19
A27: Latest common year | B27: 2024-25 | C27: Later QR years lack a matching HESA denominator
